{
  "id": "xananode.canonical:schema/relationship-type-made_of",
  "title": "Made of",
  "type": "schema",
  "subtype": "relationship_type_schema",
  "importance": 5,
  "summary": "The source physical item or structure is made of the target material or substance.",
  "version": "0.5.1",
  "registry_type": "made_of",
  "registry_namespace": "xananode",
  "category": "composition",
  "inverse": "makes_up",
  "color": "#22c55e",
  "inverse_color": "#86efac",
  "line_style": "solid",
  "inverse_line_style": "dashed",
  "default_weight": 4,
  "default_visibility": "primary",
  "relationships": []
}
