{
  "id": "xananode.canonical:schema/relationship-type-example_of",
  "title": "Example of",
  "type": "schema",
  "subtype": "relationship_type_schema",
  "importance": 5,
  "summary": "The source is an example or concrete instance of the target.",
  "version": "0.5.1",
  "registry_type": "example_of",
  "registry_namespace": "xananode",
  "category": "cognition",
  "inverse": "has_example",
  "color": "#7c3aed",
  "inverse_color": "#ddd6fe",
  "line_style": "solid",
  "inverse_line_style": "dashed",
  "default_weight": 4,
  "default_visibility": "primary",
  "relationships": []
}
